{
  "generated_at": 1784078839.2485828,
  "devices": [
    {
      "name": "iPhone 8 (Global)",
      "online": true,
      "error": "",
      "uptime": "4 days  1:27",
      "battery_pct": 100,
      "is_charging": false,
      "temp_f": 86.7,
      "temp_c": 30.4,
      "watched_processes": [
        "SpringBoard",
        "backboardd",
        "sshd"
      ],
      "process_count": 160
    },
    {
      "name": "iPhone 8 (GSM)",
      "online": true,
      "error": "",
      "uptime": "17:05",
      "battery_pct": 100,
      "is_charging": false,
      "temp_f": 85.6,
      "temp_c": 29.8,
      "watched_processes": [
        "SpringBoard",
        "backboardd",
        "sshd"
      ],
      "process_count": 301
    }
  ]
}